klab_pytest_toolkit_decorators/__init__.py
klab_pytest_toolkit_decorators/compliance.py
klab_pytest_toolkit_decorators/plugin.py
klab_pytest_toolkit_decorators-1.0.0.dist-info/METADATA
klab_pytest_toolkit_decorators-1.0.0.dist-info/WHEEL
klab_pytest_toolkit_decorators-1.0.0.dist-info/entry_points.txt
klab_pytest_toolkit_decorators-1.0.0.dist-info/RECORD
