Metadata-Version: 2.4
Name: klab-pytest-toolkit-decorators
Version: 1.0.0
Summary: Pytest decorators for the Klab Pytest Toolkit
Project-URL: Changelog, https://github.com/klab365/klab-pytest-toolkit/blob/main/CHANGELOG.md
Project-URL: Repository, https://github.com/klab365/klab-pytest-toolkit
Project-URL: Issues, https://github.com/klab365/klab-pytest-toolkit/issues
Author-email: Burak Kizilkaya <burak.kizilkaya@outlook.com>
License-Expression: MIT
Classifier: Development Status :: 3 - Alpha
Classifier: Intended Audience :: Developers
Classifier: License :: OSI Approved :: MIT License
Classifier: Programming Language :: Python :: 3
Requires-Python: <4,>=3.11
Requires-Dist: pytest>=8.3.5
